tempit/__init__.py
tempit/core.py
tempit/utils.py
tempit-0.2.3.dist-info/LICENSE
tempit-0.2.3.dist-info/METADATA
tempit-0.2.3.dist-info/WHEEL
tempit-0.2.3.dist-info/top_level.txt
tempit-0.2.3.dist-info/RECORD
