Metadata-Version: 2.1
Name: tempit
Version: 0.2.3
Summary: A dead simple time decorator
Author-email: Mario Crespo <info@mariocrespo.es>
License: MIT License
Project-URL: Repository, https://github.com/mcrespoae/tempit
Classifier: Development Status :: 5 - Production/Stable
Classifier: Programming Language :: Python :: 3
Classifier: License :: OSI Approved :: MIT License
Classifier: Operating System :: OS Independent
Classifier: Intended Audience :: Developers
Requires-Python: >=3.8
License-File: LICENSE
Requires-Dist: joblib ==1.4.2
